exploitdbsighting/conf_sample.py
exploitdbsighting/config.py
exploitdbsighting/publish.py
exploitdbsighting-0.2.0.dist-info/COPYING
exploitdbsighting-0.2.0.dist-info/METADATA
exploitdbsighting-0.2.0.dist-info/WHEEL
exploitdbsighting-0.2.0.dist-info/entry_points.txt
exploitdbsighting-0.2.0.dist-info/RECORD
