Metadata-Version: 2.1
Name: ExploitDBSighting
Version: 0.2.0
Summary: A client that retrieves vulnerability observations from Exploit-DB and pushes them to a Vulnerability-Lookup instance.
Home-page: https://github.com/cedricbonhomme/ExploitDBSighting
License: GPL-3.0-or-later
Keywords: vulnerability,cve,sighting,observations,Exploit-DB,PyVulnerabilityLookup
Author: Cédric Bonhomme
Author-email: cedric.bonhomme@circl.lu
Requires-Python: >=3.10,<4.0
Classifier: Development Status :: 5 - Production/Stable
Classifier: Environment :: Console
Classifier: Intended Audience :: Developers
Classifier: Intended Audience :: Science/Research
Classifier: License :: OSI Approved :: GNU General Public License v3 or later (GPLv3+)
Classifier: Operating System :: POSIX :: Linux
Classifier: Programming Language :: Python :: 3
Classifier: Programming Language :: Python :: 3.10
Classifier: Programming Language :: Python :: 3.11
Classifier: Programming Language :: Python :: 3.12
Classifier: Programming Language :: Python :: 3.13
Classifier: Topic :: Security
Requires-Dist: argparse (>=1.4.0,<2.0.0)
Requires-Dist: pyvulnerabilitylookup (>=2.1.0,<3.0.0)
Requires-Dist: requests (>=2.32.3,<3.0.0)
Project-URL: Repository, https://github.com/cedricbonhomme/ExploitDBSighting
